starlette_live/__init__.py
starlette_live/components.py
starlette_live/endpoints.py
starlette_live/routing.py
starlette_live/statics/live/_live.js
starlette_live/statics/live/live.js
starlette_live/templates.py
starlette_live-0.1.0.dist-info/LICENSE
starlette_live-0.1.0.dist-info/WHEEL
starlette_live-0.1.0.dist-info/METADATA
starlette_live-0.1.0.dist-info/RECORD
