Metadata-Version: 2.1
Name: starlette-live
Version: 0.1.0
Summary: Live views for Starlette.
Home-page: https://github.com/alex-oleshkevich/starlette_live
License: MIT
Author: Alex Oleshkevich
Author-email: alex.oleshkevich@gmail.com
Requires-Python: >=3.10,<4.0
Classifier: Development Status :: 5 - Production/Stable
Classifier: Environment :: Web Environment
Classifier: Intended Audience :: Developers
Classifier: License :: OSI Approved :: MIT License
Classifier: Operating System :: OS Independent
Classifier: Programming Language :: Python :: 3
Classifier: Programming Language :: Python :: 3.10
Classifier: Programming Language :: Python :: 3
Classifier: Programming Language :: Python :: 3.10
Classifier: Topic :: Software Development :: Libraries :: Python Modules
Classifier: Typing :: Typed
Requires-Dist: Jinja2 (>=3.1,<4.0)
Requires-Dist: python-multipart (>=0.0.5,<0.0.6)
Requires-Dist: starlette (>=0.20,<0.21)
Project-URL: Documentation, https://github.com/alex-oleshkevich/starlette_live
Project-URL: Repository, https://github.com/alex-oleshkevich/starlette_live
